data_portal_explorer/__init__.py
data_portal_explorer/cli.py
data_portal_explorer/data_portal_explorer.py
data_portal_explorer-0.1.12.dist-info/LICENSE
data_portal_explorer-0.1.12.dist-info/METADATA
data_portal_explorer-0.1.12.dist-info/WHEEL
data_portal_explorer-0.1.12.dist-info/entry_points.txt
data_portal_explorer-0.1.12.dist-info/top_level.txt
data_portal_explorer-0.1.12.dist-info/RECORD
