Metadata-Version: 2.1
Name: data-portal-explorer
Version: 0.1.12
Summary: This package contains tools to extract metadata from CKAN
Home-page: https://github.com/kingsdigitallab/DataPortalExplorer
Author: Kings Digital Lab
Author-email: jose.m.vieira@kcl.ac.uk
License: MIT license
Keywords: data_portal_explorer
Classifier: Development Status :: 2 - Pre-Alpha
Classifier: Intended Audience :: Developers
Classifier: License :: OSI Approved :: MIT License
Classifier: Natural Language :: English
Classifier: Programming Language :: Python :: 3
Classifier: Programming Language :: Python :: 3.7
License-File: LICENSE
Requires-Dist: ckanapi <5,>=4
Requires-Dist: click <8,>=7
Requires-Dist: pandas <2
Requires-Dist: tqdm <5,>=4
Requires-Dist: xlrd <1.3,>=1.2
